{
  "id": "GraficaAcumulado_Estacion1",
  "kind": "graph",
  "format": "json",
  "x": [
    0,
    1,
    2,
    3,
    4,
    5,
    6,
    7,
    8,
    9,
    10,
    11,
    12,
    13,
    14,
    15,
    16,
    17,
    18,
    19,
    20,
    21,
    22,
    23
  ],
  "series": {
    "cum": [
      1480.0,
      2975.0,
      4470.0,
      5965.0,
      7460.0,
      8955.0,
      10441.25,
      11845.0,
      13151.25,
      14340.0,
      15546.25,
      16708.75,
      17878.75,
      18976.25,
      20095.0,
      21377.5,
      22606.25,
      23803.75,
      24938.75,
      25953.75,
      26977.5,
      28152.5,
      29470.0,
      30918.75
    ]
  },
  "meta": {
    "type": "line",
    "title": "Acumulado Estación 1",
    "xLabel": "Hora",
    "yLabel": "Acumulado"
  }
}